<?xml version="1.0" encoding="UTF-8"?>
<!-- Generated with Moodle XML Converter https://moodlexml.fly.dev -->
<quiz>
  <question type="category">
    <category>
      <text>__Category Name__</text>
    </category>
  </question>
  <!-- Question entry 1 -->
  <question type="multichoice">
    <name>
      <text>
        <![CDATA[__Question 1]]>
      </text>
    </name>
    <questiontext format="html">
      <text>
        <![CDATA[What was the primary factor contributing to systemic discrimination and socioeconomic disparities for Indigenous populations in Canada?]]>
      </text>
    </questiontext>
    <answer fraction="0">
      <text>
        <![CDATA[The introduction of universal healthcare]]>
      </text>
    </answer>
    <answer fraction="100.000">
      <text>
        <![CDATA[The Indian Act and residential schools]]>
      </text>
    </answer>
    <answer fraction="0">
      <text>
        <![CDATA[The expansion of the welfare state]]>
      </text>
    </answer>
    <answer fraction="0">
      <text>
        <![CDATA[The rise of industrialization]]>
      </text>
    </answer>
    <shuffleanswers>0</shuffleanswers>
    <single>true</single>
    <answernumbering>123</answernumbering>
  </question>
  <!-- Question entry 2 -->
  <question type="multichoice">
    <name>
      <text>
        <![CDATA[__Question 2]]>
      </text>
    </name>
    <questiontext format="html">
      <text>
        <![CDATA[According to the OECD, how much more does the richest 10% earn compared to the poorest 10% in its member countries?]]>
      </text>
    </questiontext>
    <answer fraction="0">
      <text>
        <![CDATA[5.2 times]]>
      </text>
    </answer>
    <answer fraction="0">
      <text>
        <![CDATA[7.8 times]]>
      </text>
    </answer>
    <answer fraction="100.000">
      <text>
        <![CDATA[9.6 times]]>
      </text>
    </answer>
    <answer fraction="0">
      <text>
        <![CDATA[12.3 times]]>
      </text>
    </answer>
    <shuffleanswers>0</shuffleanswers>
    <single>true</single>
    <answernumbering>123</answernumbering>
  </question>
  <!-- Question entry 3 -->
  <question type="multichoice">
    <name>
      <text>
        <![CDATA[__Question 3]]>
      </text>
    </name>
    <questiontext format="html">
      <text>
        <![CDATA[What was a key characteristic of income inequality in Canada between 1946 and 1981?]]>
      </text>
    </questiontext>
    <answer fraction="0">
      <text>
        <![CDATA[It fluctuated significantly due to market volatility]]>
      </text>
    </answer>
    <answer fraction="100.000">
      <text>
        <![CDATA[It remained relatively stable despite economic transformations]]>
      </text>
    </answer>
    <answer fraction="0">
      <text>
        <![CDATA[It declined steadily due to redistributive policies]]>
      </text>
    </answer>
    <answer fraction="0">
      <text>
        <![CDATA[It increased at an accelerating rate]]>
      </text>
    </answer>
    <shuffleanswers>0</shuffleanswers>
    <single>true</single>
    <answernumbering>123</answernumbering>
  </question>
  <!-- Question entry 4 -->
  <question type="multichoice">
    <name>
      <text>
        <![CDATA[__Question 4]]>
      </text>
    </name>
    <questiontext format="html">
      <text>
        <![CDATA[What is the main critique of the "Income Inequality Hypothesis" regarding health outcomes?]]>
      </text>
    </questiontext>
    <answer fraction="100.000">
      <text>
        <![CDATA[It fails to consider absolute income levels]]>
      </text>
    </answer>
    <answer fraction="0">
      <text>
        <![CDATA[It overemphasizes social spending policies]]>
      </text>
    </answer>
    <answer fraction="0">
      <text>
        <![CDATA[It assumes health disparities are unrelated to income]]>
      </text>
    </answer>
    <answer fraction="0">
      <text>
        <![CDATA[It ignores the role of economic mobility]]>
      </text>
    </answer>
    <shuffleanswers>0</shuffleanswers>
    <single>true</single>
    <answernumbering>123</answernumbering>
  </question>
  <!-- Question entry 5 -->
  <question type="multichoice">
    <name>
      <text>
        <![CDATA[__Question 5]]>
      </text>
    </name>
    <questiontext format="html">
      <text>
        <![CDATA[What is a significant factor contributing to widening wealth inequality in Canada?]]>
      </text>
    </questiontext>
    <answer fraction="0">
      <text>
        <![CDATA[Increased social spending on education]]>
      </text>
    </answer>
    <answer fraction="100.000">
      <text>
        <![CDATA[Growth in financial and real estate assets among wealthier groups]]>
      </text>
    </answer>
    <answer fraction="0">
      <text>
        <![CDATA[Declining corporate tax rates]]>
      </text>
    </answer>
    <answer fraction="0">
      <text>
        <![CDATA[A rise in manufacturing jobs]]>
      </text>
    </answer>
    <shuffleanswers>0</shuffleanswers>
    <single>true</single>
    <answernumbering>123</answernumbering>
  </question>
  <!-- Question entry 6 -->
  <question type="multichoice">
    <name>
      <text>
        <![CDATA[__Question 6]]>
      </text>
    </name>
    <questiontext format="html">
      <text>
        <![CDATA[What is one key factor explaining lower educational attainment among Indigenous communities in Canada?]]>
      </text>
    </questiontext>
    <answer fraction="0">
      <text>
        <![CDATA[A lack of available financial aid]]>
      </text>
    </answer>
    <answer fraction="100.000">
      <text>
        <![CDATA[Systemic barriers and historical discrimination]]>
      </text>
    </answer>
    <answer fraction="0">
      <text>
        <![CDATA[A lower emphasis on higher education within these communities]]>
      </text>
    </answer>
    <answer fraction="0">
      <text>
        <![CDATA[An overall decline in post-secondary enrollment rates]]>
      </text>
    </answer>
    <shuffleanswers>0</shuffleanswers>
    <single>true</single>
    <answernumbering>123</answernumbering>
  </question>
  <!-- Question entry 7 -->
  <question type="multichoice">
    <name>
      <text>
        <![CDATA[__Question 7]]>
      </text>
    </name>
    <questiontext format="html">
      <text>
        <![CDATA[If a country has a Gini coefficient of 0.45, it means:]]>
      </text>
    </questiontext>
    <answer fraction="0">
      <text>
        <![CDATA[The richest 10% of the population earns 45% of the total income]]>
      </text>
    </answer>
    <answer fraction="0">
      <text>
        <![CDATA[The country has perfect equality]]>
      </text>
    </answer>
    <answer fraction="0">
      <text>
        <![CDATA[45% of the population is below the poverty line]]>
      </text>
    </answer>
    <answer fraction="100.000">
      <text>
        <![CDATA[Income distribution is more unequal than a country with a Gini of 0.3]]>
      </text>
    </answer>
    <shuffleanswers>0</shuffleanswers>
    <single>true</single>
    <answernumbering>123</answernumbering>
  </question>
  <!-- Question entry 8 -->
  <question type="multichoice">
    <name>
      <text>
        <![CDATA[__Question 8]]>
      </text>
    </name>
    <questiontext format="html">
      <text>
        <![CDATA[A Lorenz curve that is farther from the equality line indicates:]]>
      </text>
    </questiontext>
    <answer fraction="0">
      <text>
        <![CDATA[A lower Gini coefficient]]>
      </text>
    </answer>
    <answer fraction="0">
      <text>
        <![CDATA[Higher economic mobility]]>
      </text>
    </answer>
    <answer fraction="100.000">
      <text>
        <![CDATA[A more unequal income distribution]]>
      </text>
    </answer>
    <answer fraction="0">
      <text>
        <![CDATA[A perfectly equal income distribution]]>
      </text>
    </answer>
    <shuffleanswers>0</shuffleanswers>
    <single>true</single>
    <answernumbering>123</answernumbering>
  </question>
  <!-- Question entry 9 -->
  <question type="multichoice">
    <name>
      <text>
        <![CDATA[__Question 9]]>
      </text>
    </name>
    <questiontext format="html">
      <text>
        <![CDATA[Which of the following statements about median and mean income is correct?]]>
      </text>
    </questiontext>
    <answer fraction="0">
      <text>
        <![CDATA[Mean income is always lower than median income]]>
      </text>
    </answer>
    <answer fraction="100.000">
      <text>
        <![CDATA[A growing gap between mean and median income indicates rising inequality]]>
      </text>
    </answer>
    <answer fraction="0">
      <text>
        <![CDATA[Median income is always higher than mean income]]>
      </text>
    </answer>
    <answer fraction="0">
      <text>
        <![CDATA[The median is affected by extreme values more than the mean]]>
      </text>
    </answer>
    <shuffleanswers>0</shuffleanswers>
    <single>true</single>
    <answernumbering>123</answernumbering>
  </question>
  <!-- Question entry 10 -->
  <question type="multichoice">
    <name>
      <text>
        <![CDATA[__Question 10]]>
      </text>
    </name>
    <questiontext format="html">
      <text>
        <![CDATA[The Market Basket Measure (MBM) defines poverty based on:]]>
      </text>
    </questiontext>
    <answer fraction="0">
      <text>
        <![CDATA[The share of national income going to the bottom 10%]]>
      </text>
    </answer>
    <answer fraction="100.000">
      <text>
        <![CDATA[The cost of a specific basket of basic goods and services]]>
      </text>
    </answer>
    <answer fraction="0">
      <text>
        <![CDATA[The percentage of people earning below half of the mean income]]>
      </text>
    </answer>
    <answer fraction="0">
      <text>
        <![CDATA[The minimum wage set by the government]]>
      </text>
    </answer>
    <shuffleanswers>0</shuffleanswers>
    <single>true</single>
    <answernumbering>123</answernumbering>
  </question>
  <!-- Question entry 11 -->
  <question type="multichoice">
    <name>
      <text>
        <![CDATA[__Question 11]]>
      </text>
    </name>
    <questiontext format="html">
      <text>
        <![CDATA[When comparing inequality across countries using the Gini coefficient, it is crucial to:]]>
      </text>
    </questiontext>
    <answer fraction="100.000">
      <text>
        <![CDATA[Ensure that data sources and income definitions are consistent]]>
      </text>
    </answer>
    <answer fraction="0">
      <text>
        <![CDATA[Use only pre-tax income for a fair comparison]]>
      </text>
    </answer>
    <answer fraction="0">
      <text>
        <![CDATA[Ignore country-specific economic structures]]>
      </text>
    </answer>
    <answer fraction="0">
      <text>
        <![CDATA[Assume all countries have the same population size]]>
      </text>
    </answer>
    <shuffleanswers>0</shuffleanswers>
    <single>true</single>
    <answernumbering>123</answernumbering>
  </question>
  <!-- Question entry 12 -->
  <question type="multichoice">
    <name>
      <text>
        <![CDATA[__Question 12]]>
      </text>
    </name>
    <questiontext format="html">
      <text>
        <![CDATA[If the Gini coefficient of a country is 0.8, it suggests that:]]>
      </text>
    </questiontext>
    <answer fraction="0">
      <text>
        <![CDATA[Income is equally distributed]]>
      </text>
    </answer>
    <answer fraction="100.000">
      <text>
        <![CDATA[Almost all income is concentrated in a few individuals]]>
      </text>
    </answer>
    <answer fraction="0">
      <text>
        <![CDATA[The bottom 50% of the population earns at least 50% of total income]]>
      </text>
    </answer>
    <answer fraction="0">
      <text>
        <![CDATA[The country has no poverty]]>
      </text>
    </answer>
    <shuffleanswers>0</shuffleanswers>
    <single>true</single>
    <answernumbering>123</answernumbering>
  </question>
  <!-- Question entry 13 -->
  <question type="multichoice">
    <name>
      <text>
        <![CDATA[__Question 13]]>
      </text>
    </name>
    <questiontext format="html">
      <text>
        <![CDATA[The evolution of the Gini coefficient in Canada suggests:]]>
      </text>
    </questiontext>
    <answer fraction="0">
      <text>
        <![CDATA[It has been consistently decreasing since 1970]]>
      </text>
    </answer>
    <answer fraction="100.000">
      <text>
        <![CDATA[It increased in the 1990s and then started declining in the 2000s]]>
      </text>
    </answer>
    <answer fraction="0">
      <text>
        <![CDATA[It remained constant across all decades]]>
      </text>
    </answer>
    <answer fraction="0">
      <text>
        <![CDATA[The richest quintile lost income share over time]]>
      </text>
    </answer>
    <shuffleanswers>0</shuffleanswers>
    <single>true</single>
    <answernumbering>123</answernumbering>
  </question>
  <!-- Question entry 14 -->
  <question type="multichoice">
    <name>
      <text>
        <![CDATA[__Question 14]]>
      </text>
    </name>
    <questiontext format="html">
      <text>
        <![CDATA[If all income gains in an economy go to the top 10%, the Gini coefficient will:]]>
      </text>
    </questiontext>
    <answer fraction="0">
      <text>
        <![CDATA[Decrease]]>
      </text>
    </answer>
    <answer fraction="0">
      <text>
        <![CDATA[Remain unchanged]]>
      </text>
    </answer>
    <answer fraction="100.000">
      <text>
        <![CDATA[Increase]]>
      </text>
    </answer>
    <answer fraction="0">
      <text>
        <![CDATA[Approach zero]]>
      </text>
    </answer>
    <shuffleanswers>0</shuffleanswers>
    <single>true</single>
    <answernumbering>123</answernumbering>
  </question>
  <!-- Question entry 15 -->
  <question type="multichoice">
    <name>
      <text>
        <![CDATA[__Question 15]]>
      </text>
    </name>
    <questiontext format="html">
      <text>
        <![CDATA[Which of the following is an empirical observation about inequality and growth?]]>
      </text>
    </questiontext>
    <answer fraction="0">
      <text>
        <![CDATA[All high-income countries have low inequality]]>
      </text>
    </answer>
    <answer fraction="100.000">
      <text>
        <![CDATA[There is no clear relationship between GDP growth and inequality]]>
      </text>
    </answer>
    <answer fraction="0">
      <text>
        <![CDATA[Economic growth always leads to lower inequality]]>
      </text>
    </answer>
    <answer fraction="0">
      <text>
        <![CDATA[Inequality is highest in countries with no economic growth]]>
      </text>
    </answer>
    <shuffleanswers>0</shuffleanswers>
    <single>true</single>
    <answernumbering>123</answernumbering>
  </question>
  <!-- Question entry 16 -->
  <question type="multichoice">
    <name>
      <text>
        <![CDATA[__Question 16]]>
      </text>
    </name>
    <questiontext format="html">
      <text>
        <![CDATA[The relationship between poverty and inequality in empirical studies suggests:]]>
      </text>
    </questiontext>
    <answer fraction="100.000">
      <text>
        <![CDATA[There is no necessary link between poverty and inequality]]>
      </text>
    </answer>
    <answer fraction="0">
      <text>
        <![CDATA[All high-inequality countries have high poverty]]>
      </text>
    </answer>
    <answer fraction="0">
      <text>
        <![CDATA[A lower Gini coefficient always eliminates poverty]]>
      </text>
    </answer>
    <answer fraction="0">
      <text>
        <![CDATA[Poverty levels are unaffected by inequality]]>
      </text>
    </answer>
    <shuffleanswers>0</shuffleanswers>
    <single>true</single>
    <answernumbering>123</answernumbering>
  </question>
  <!-- Question entry 17 -->
  <question type="multichoice">
    <name>
      <text>
        <![CDATA[__Question 17]]>
      </text>
    </name>
    <questiontext format="html">
      <text>
        <![CDATA[A decreasing poverty rate with a stable Gini coefficient suggests that:]]>
      </text>
    </questiontext>
    <answer fraction="0">
      <text>
        <![CDATA[Inequality has worsened]]>
      </text>
    </answer>
    <answer fraction="100.000">
      <text>
        <![CDATA[Income growth has benefited the poor without changing relative inequality]]>
      </text>
    </answer>
    <answer fraction="0">
      <text>
        <![CDATA[The middle class is shrinking]]>
      </text>
    </answer>
    <answer fraction="0">
      <text>
        <![CDATA[The bottom 10% lost income share]]>
      </text>
    </answer>
    <shuffleanswers>0</shuffleanswers>
    <single>true</single>
    <answernumbering>123</answernumbering>
  </question>
  <!-- Question entry 18 -->
  <question type="multichoice">
    <name>
      <text>
        <![CDATA[__Question 18]]>
      </text>
    </name>
    <questiontext format="html">
      <text>
        <![CDATA[The labor force participation rate is 65%, and the working-age population is 200 million. If the unemployment rate is 6%, how many people are unemployed?]]>
      </text>
    </questiontext>
    <answer fraction="0">
      <text>
        <![CDATA[7.8 million]]>
      </text>
    </answer>
    <answer fraction="0">
      <text>
        <![CDATA[8.6 million]]>
      </text>
    </answer>
    <answer fraction="100.000">
      <text>
        <![CDATA[9.1 million]]>
      </text>
    </answer>
    <answer fraction="0">
      <text>
        <![CDATA[10.4 million]]>
      </text>
    </answer>
    <shuffleanswers>0</shuffleanswers>
    <single>true</single>
    <answernumbering>123</answernumbering>
  </question>
  <!-- Question entry 19 -->
  <question type="multichoice">
    <name>
      <text>
        <![CDATA[__Question 19]]>
      </text>
    </name>
    <questiontext format="html">
      <text>
        <![CDATA[A country’s total employment is 150 million, and its total unemployment is 10 million. What is the unemployment rate?]]>
      </text>
    </questiontext>
    <answer fraction="0">
      <text>
        <![CDATA[5.8%]]>
      </text>
    </answer>
    <answer fraction="100.000">
      <text>
        <![CDATA[6.3%]]>
      </text>
    </answer>
    <answer fraction="0">
      <text>
        <![CDATA[6.5%]]>
      </text>
    </answer>
    <answer fraction="0">
      <text>
        <![CDATA[7.1%]]>
      </text>
    </answer>
    <shuffleanswers>0</shuffleanswers>
    <single>true</single>
    <answernumbering>123</answernumbering>
  </question>
  <!-- Question entry 20 -->
  <question type="multichoice">
    <name>
      <text>
        <![CDATA[__Question 20]]>
      </text>
    </name>
    <questiontext format="html">
      <text>
        <![CDATA[The natural rate of unemployment is 4%, and the actual unemployment rate is 7%. If the labor force is 120 million, how many workers are cyclically unemployed?]]>
      </text>
    </questiontext>
    <answer fraction="100.000">
      <text>
        <![CDATA[3.6 million]]>
      </text>
    </answer>
    <answer fraction="0">
      <text>
        <![CDATA[4.2 million]]>
      </text>
    </answer>
    <answer fraction="0">
      <text>
        <![CDATA[3.9 million]]>
      </text>
    </answer>
    <answer fraction="0">
      <text>
        <![CDATA[4.8 million]]>
      </text>
    </answer>
    <shuffleanswers>0</shuffleanswers>
    <single>true</single>
    <answernumbering>123</answernumbering>
  </question>
  <!-- Question entry 21 -->
  <question type="multichoice">
    <name>
      <text>
        <![CDATA[__Question 21]]>
      </text>
    </name>
    <questiontext format="html">
      <text>
        <![CDATA[Suppose an economy experiences an increase in discouraged workers from 2 million to 5 million while the labor force remains constant at 160 million. What happens to the official unemployment rate if the number of unemployed workers was originally 12 million?]]>
      </text>
    </questiontext>
    <answer fraction="100.000">
      <text>
        <![CDATA[Falls to 5.6%]]>
      </text>
    </answer>
    <answer fraction="0">
      <text>
        <![CDATA[Falls to 4.7%]]>
      </text>
    </answer>
    <answer fraction="0">
      <text>
        <![CDATA[Rises to 9.2%]]>
      </text>
    </answer>
    <answer fraction="0">
      <text>
        <![CDATA[Remains at 7.5%]]>
      </text>
    </answer>
    <shuffleanswers>0</shuffleanswers>
    <single>true</single>
    <answernumbering>123</answernumbering>
  </question>
  <!-- Question entry 22 -->
  <question type="multichoice">
    <name>
      <text>
        <![CDATA[__Question 22]]>
      </text>
    </name>
    <questiontext format="html">
      <text>
        <![CDATA[Suppose a country has a frictional unemployment rate of 2.5%, a structural unemployment rate of 3%, and an actual unemployment rate of 8%. What is the cyclical unemployment rate?]]>
      </text>
    </questiontext>
    <answer fraction="0">
      <text>
        <![CDATA[2.5%]]>
      </text>
    </answer>
    <answer fraction="0">
      <text>
        <![CDATA[3.0%]]>
      </text>
    </answer>
    <answer fraction="100.000">
      <text>
        <![CDATA[5.0%]]>
      </text>
    </answer>
    <answer fraction="0">
      <text>
        <![CDATA[5.5%]]>
      </text>
    </answer>
    <shuffleanswers>0</shuffleanswers>
    <single>true</single>
    <answernumbering>123</answernumbering>
  </question>
  <!-- Question entry 23 -->
  <question type="multichoice">
    <name>
      <text>
        <![CDATA[__Question 23]]>
      </text>
    </name>
    <questiontext format="html">
      <text>
        <![CDATA[Which category of workers is most vulnerable to automation according to labor market polarization?]]>
      </text>
    </questiontext>
    <answer fraction="0">
      <text>
        <![CDATA[High-skilled workers]]>
      </text>
    </answer>
    <answer fraction="100.000">
      <text>
        <![CDATA[Middle-skilled workers]]>
      </text>
    </answer>
    <answer fraction="0">
      <text>
        <![CDATA[Low-skilled workers]]>
      </text>
    </answer>
    <answer fraction="0">
      <text>
        <![CDATA[All workers equally]]>
      </text>
    </answer>
    <shuffleanswers>0</shuffleanswers>
    <single>true</single>
    <answernumbering>123</answernumbering>
  </question>
  <!-- Question entry 24 -->
  <question type="multichoice">
    <name>
      <text>
        <![CDATA[__Question 24]]>
      </text>
    </name>
    <questiontext format="html">
      <text>
        <![CDATA[What is a key factor in ensuring workers can transition to new roles after automation-induced displacement?]]>
      </text>
    </questiontext>
    <answer fraction="0">
      <text>
        <![CDATA[Wage subsidies]]>
      </text>
    </answer>
    <answer fraction="0">
      <text>
        <![CDATA[Increased automation]]>
      </text>
    </answer>
    <answer fraction="100.000">
      <text>
        <![CDATA[Retraining and education]]>
      </text>
    </answer>
    <answer fraction="0">
      <text>
        <![CDATA[Reduced taxation]]>
      </text>
    </answer>
    <shuffleanswers>0</shuffleanswers>
    <single>true</single>
    <answernumbering>123</answernumbering>
  </question>
  <!-- Question entry 25 -->
  <question type="multichoice">
    <name>
      <text>
        <![CDATA[__Question 25]]>
      </text>
    </name>
    <questiontext format="html">
      <text>
        <![CDATA[What is the predicted effect of automation on routine work wages?]]>
      </text>
    </questiontext>
    <answer fraction="0">
      <text>
        <![CDATA[Increase due to efficiency]]>
      </text>
    </answer>
    <answer fraction="100.000">
      <text>
        <![CDATA[Decrease due to reduced demand]]>
      </text>
    </answer>
    <answer fraction="0">
      <text>
        <![CDATA[Remain unchanged]]>
      </text>
    </answer>
    <answer fraction="0">
      <text>
        <![CDATA[Increase due to government intervention]]>
      </text>
    </answer>
    <shuffleanswers>0</shuffleanswers>
    <single>true</single>
    <answernumbering>123</answernumbering>
  </question>
  <!-- Question entry 26 -->
  <question type="multichoice">
    <name>
      <text>
        <![CDATA[__Question 26]]>
      </text>
    </name>
    <questiontext format="html">
      <text>
        <![CDATA[Which policy is NOT mentioned in the lecture as a response to automation’s labor effects?]]>
      </text>
    </questiontext>
    <answer fraction="0">
      <text>
        <![CDATA[Universal Basic Income (UBI)]]>
      </text>
    </answer>
    <answer fraction="0">
      <text>
        <![CDATA[Strengthening unemployment insurance]]>
      </text>
    </answer>
    <answer fraction="100.000">
      <text>
        <![CDATA[Restricting automation use]]>
      </text>
    </answer>
    <answer fraction="0">
      <text>
        <![CDATA[Wage insurance and job placement services]]>
      </text>
    </answer>
    <shuffleanswers>0</shuffleanswers>
    <single>true</single>
    <answernumbering>123</answernumbering>
  </question>
  <!-- Question entry 27 -->
  <question type="multichoice">
    <name>
      <text>
        <![CDATA[__Question 27]]>
      </text>
    </name>
    <questiontext format="html">
      <text>
        <![CDATA[A labor force of 100,000 is divided into 20% high-skilled, 50% middle-skilled, and 30% low-skilled workers. Demand changes as follows: o High-skilled: +15% o Middle-skilled: -25% o Low-skilled: 0% What is the total net change in workforce size?]]>
      </text>
    </questiontext>
    <answer fraction="100.000">
      <text>
        <![CDATA[-9,500]]>
      </text>
    </answer>
    <answer fraction="0">
      <text>
        <![CDATA[-12,500]]>
      </text>
    </answer>
    <answer fraction="0">
      <text>
        <![CDATA[-8,000]]>
      </text>
    </answer>
    <answer fraction="0">
      <text>
        <![CDATA[-10,000]]>
      </text>
    </answer>
    <shuffleanswers>0</shuffleanswers>
    <single>true</single>
    <answernumbering>123</answernumbering>
  </question>
  <!-- Question entry 28 -->
  <question type="multichoice">
    <name>
      <text>
        <![CDATA[__Question 28]]>
      </text>
    </name>
    <questiontext format="html">
      <text>
        <![CDATA[A country has 10 million workers, and 40% of jobs are at risk of automation. For every lost job, 0.75 new jobs are created. What is the net change in jobs?]]>
      </text>
    </questiontext>
    <answer fraction="100.000">
      <text>
        <![CDATA[-1 million]]>
      </text>
    </answer>
    <answer fraction="0">
      <text>
        <![CDATA[-500,000]]>
      </text>
    </answer>
    <answer fraction="0">
      <text>
        <![CDATA[-2 million]]>
      </text>
    </answer>
    <answer fraction="0">
      <text>
        <![CDATA[-3 million]]>
      </text>
    </answer>
    <shuffleanswers>0</shuffleanswers>
    <single>true</single>
    <answernumbering>123</answernumbering>
  </question>
  <!-- Question entry 29 -->
  <question type="multichoice">
    <name>
      <text>
        <![CDATA[__Question 29]]>
      </text>
    </name>
    <questiontext format="html">
      <text>
        <![CDATA[A high-skilled sector has 3M workers earning $80,000, with a 10% wage increase. A routine work sector has 3M workers earning $40,000, with a 5% wage decrease. What is the total wage change?]]>
      </text>
    </questiontext>
    <answer fraction="100.000">
      <text>
        <![CDATA[$18 billion increase]]>
      </text>
    </answer>
    <answer fraction="0">
      <text>
        <![CDATA[$15 billion decrease]]>
      </text>
    </answer>
    <answer fraction="0">
      <text>
        <![CDATA[$20 billion increase]]>
      </text>
    </answer>
    <answer fraction="0">
      <text>
        <![CDATA[$12 billion increase]]>
      </text>
    </answer>
    <shuffleanswers>0</shuffleanswers>
    <single>true</single>
    <answernumbering>123</answernumbering>
  </question>
  <!-- Question entry 30 -->
  <question type="multichoice">
    <name>
      <text>
        <![CDATA[__Question 30]]>
      </text>
    </name>
    <questiontext format="html">
      <text>
        <![CDATA[A country retrains 1M workers at $2,000 per worker. If 70% find jobs at $50,000 (previously $30,000), what is the wage gain?]]>
      </text>
    </questiontext>
    <answer fraction="0">
      <text>
        <![CDATA[$10B]]>
      </text>
    </answer>
    <answer fraction="0">
      <text>
        <![CDATA[$12B]]>
      </text>
    </answer>
    <answer fraction="100.000">
      <text>
        <![CDATA[$14B]]>
      </text>
    </answer>
    <answer fraction="0">
      <text>
        <![CDATA[$16B]]>
      </text>
    </answer>
    <shuffleanswers>0</shuffleanswers>
    <single>true</single>
    <answernumbering>123</answernumbering>
  </question>
  <!-- Question entry 31 -->
  <question type="multichoice">
    <name>
      <text>
        <![CDATA[__Question 31]]>
      </text>
    </name>
    <questiontext format="html">
      <text>
        <![CDATA[A labor force of 50M has an initial participation rate of 62%. If automation displaces 2M workers, what is the new participation rate assuming no reentry into the workforce?]]>
      </text>
    </questiontext>
    <answer fraction="0">
      <text>
        <![CDATA[58%]]>
      </text>
    </answer>
    <answer fraction="100.000">
      <text>
        <![CDATA[60%]]>
      </text>
    </answer>
    <answer fraction="0">
      <text>
        <![CDATA[56%]]>
      </text>
    </answer>
    <answer fraction="0">
      <text>
        <![CDATA[54%]]>
      </text>
    </answer>
    <shuffleanswers>0</shuffleanswers>
    <single>true</single>
    <answernumbering>123</answernumbering>
  </question>
  <!-- Question entry 32 -->
  <question type="multichoice">
    <name>
      <text>
        <![CDATA[__Question 32]]>
      </text>
    </name>
    <questiontext format="html">
      <text>
        <![CDATA[If manufacturing loses 500,000 jobs, but 350,000 new AI-related jobs are created, what is the percentage decline in total jobs?]]>
      </text>
    </questiontext>
    <answer fraction="0">
      <text>
        <![CDATA[2%]]>
      </text>
    </answer>
    <answer fraction="0">
      <text>
        <![CDATA[1.5%]]>
      </text>
    </answer>
    <answer fraction="0">
      <text>
        <![CDATA[3%]]>
      </text>
    </answer>
    <answer fraction="100.000">
      <text>
        <![CDATA[1%]]>
      </text>
    </answer>
    <shuffleanswers>0</shuffleanswers>
    <single>true</single>
    <answernumbering>123</answernumbering>
  </question>
  <!-- Question entry 33 -->
  <question type="multichoice">
    <name>
      <text>
        <![CDATA[__Question 33]]>
      </text>
    </name>
    <questiontext format="html">
      <text>
        <![CDATA[Before AI, 5M people were unemployed in a 100M labor force. After AI displaced 1M jobs, how does the unemployment rate change?]]>
      </text>
    </questiontext>
    <answer fraction="0">
      <text>
        <![CDATA[6%]]>
      </text>
    </answer>
    <answer fraction="0">
      <text>
        <![CDATA[5.5%]]>
      </text>
    </answer>
    <answer fraction="100.000">
      <text>
        <![CDATA[7%]]>
      </text>
    </answer>
    <answer fraction="0">
      <text>
        <![CDATA[6.5%]]>
      </text>
    </answer>
    <shuffleanswers>0</shuffleanswers>
    <single>true</single>
    <answernumbering>123</answernumbering>
  </question>
  <!-- Question entry 34 -->
  <question type="multichoice">
    <name>
      <text>
        <![CDATA[__Question 34]]>
      </text>
    </name>
    <questiontext format="html">
      <text>
        <![CDATA[If wages in AI-related industries grow by 8% annually while traditional industries grow by 3%, what is the wage difference after 5 years for an initial wage of $50,000?]]>
      </text>
    </questiontext>
    <answer fraction="100.000">
      <text>
        <![CDATA[$15,500]]>
      </text>
    </answer>
    <answer fraction="0">
      <text>
        <![CDATA[$12,800]]>
      </text>
    </answer>
    <answer fraction="0">
      <text>
        <![CDATA[$18,200]]>
      </text>
    </answer>
    <answer fraction="0">
      <text>
        <![CDATA[$10,000]]>
      </text>
    </answer>
    <shuffleanswers>0</shuffleanswers>
    <single>true</single>
    <answernumbering>123</answernumbering>
  </question>
  <!-- Question entry 35 -->
  <question type="multichoice">
    <name>
      <text>
        <![CDATA[__Question 35]]>
      </text>
    </name>
    <questiontext format="html">
      <text>
        <![CDATA[A small business has 10 employees. The wage subsidy covers 50% of the wages, and each worker earns $3,200 per month. What is the total cost of the business payroll after the subsidy is applied?]]>
      </text>
    </questiontext>
    <answer fraction="0">
      <text>
        <![CDATA[$16,000]]>
      </text>
    </answer>
    <answer fraction="0">
      <text>
        <![CDATA[$32,000]]>
      </text>
    </answer>
    <answer fraction="0">
      <text>
        <![CDATA[$28,000]]>
      </text>
    </answer>
    <answer fraction="100.000">
      <text>
        <![CDATA[$24,000]]>
      </text>
    </answer>
    <shuffleanswers>0</shuffleanswers>
    <single>true</single>
    <answernumbering>123</answernumbering>
  </question>
  <!-- Question entry 36 -->
  <question type="multichoice">
    <name>
      <text>
        <![CDATA[__Question 36]]>
      </text>
    </name>
    <questiontext format="html">
      <text>
        <![CDATA[A company has 20 employees. The wage subsidy program pays $800 per worker each month. How much total subsidy does the company receive in one year?]]>
      </text>
    </questiontext>
    <answer fraction="0">
      <text>
        <![CDATA[$160,000]]>
      </text>
    </answer>
    <answer fraction="100.000">
      <text>
        <![CDATA[$192,000]]>
      </text>
    </answer>
    <answer fraction="0">
      <text>
        <![CDATA[$240,000]]>
      </text>
    </answer>
    <answer fraction="0">
      <text>
        <![CDATA[$100,000]]>
      </text>
    </answer>
    <shuffleanswers>0</shuffleanswers>
    <single>true</single>
    <answernumbering>123</answernumbering>
  </question>
  <!-- Question entry 37 -->
  <question type="multichoice">
    <name>
      <text>
        <![CDATA[__Question 37]]>
      </text>
    </name>
    <questiontext format="html">
      <text>
        <![CDATA[A business receives a wage subsidy of $1,500 per worker for 12 employees. If the average wage per worker is $4,000, how much does the wage subsidy reduce the total payroll expenses for the business?]]>
      </text>
    </questiontext>
    <answer fraction="0">
      <text>
        <![CDATA[$18,000]]>
      </text>
    </answer>
    <answer fraction="0">
      <text>
        <![CDATA[$10,800]]>
      </text>
    </answer>
    <answer fraction="100.000">
      <text>
        <![CDATA[$12,000]]>
      </text>
    </answer>
    <answer fraction="0">
      <text>
        <![CDATA[$15,000]]>
      </text>
    </answer>
    <shuffleanswers>0</shuffleanswers>
    <single>true</single>
    <answernumbering>123</answernumbering>
  </question>
  <!-- Question entry 38 -->
  <question type="multichoice">
    <name>
      <text>
        <![CDATA[__Question 38]]>
      </text>
    </name>
    <questiontext format="html">
      <text>
        <![CDATA[A study found that in 2020, 12% of the workforce in country X was employed in gig work. In 2025, this figure is projected to rise to 18%. If the total workforce in country X is projected to be 20 million by 2025, how many gig workers will there be in 2025?]]>
      </text>
    </questiontext>
    <answer fraction="0">
      <text>
        <![CDATA[2.5 million]]>
      </text>
    </answer>
    <answer fraction="0">
      <text>
        <![CDATA[3 million]]>
      </text>
    </answer>
    <answer fraction="100.000">
      <text>
        <![CDATA[3.6 million]]>
      </text>
    </answer>
    <answer fraction="0">
      <text>
        <![CDATA[4.5 million]]>
      </text>
    </answer>
    <shuffleanswers>0</shuffleanswers>
    <single>true</single>
    <answernumbering>123</answernumbering>
  </question>
  <!-- Question entry 39 -->
  <question type="multichoice">
    <name>
      <text>
        <![CDATA[__Question 39]]>
      </text>
    </name>
    <questiontext format="html">
      <text>
        <![CDATA[A report indicates that the hourly wage for gig economy workers increased by 8% from $15 to $16.20 over a year. What was the percentage increase in the hourly wage for gig workers?]]>
      </text>
    </questiontext>
    <answer fraction="0">
      <text>
        <![CDATA[6.5%]]>
      </text>
    </answer>
    <answer fraction="0">
      <text>
        <![CDATA[7.5%]]>
      </text>
    </answer>
    <answer fraction="100.000">
      <text>
        <![CDATA[8%]]>
      </text>
    </answer>
    <answer fraction="0">
      <text>
        <![CDATA[10%]]>
      </text>
    </answer>
    <shuffleanswers>0</shuffleanswers>
    <single>true</single>
    <answernumbering>123</answernumbering>
  </question>
  <!-- Question entry 40 -->
  <question type="multichoice">
    <name>
      <text>
        <![CDATA[__Question 40]]>
      </text>
    </name>
    <questiontext format="html">
      <text>
        <![CDATA[In a country with a total labor force of 30 million, it was estimated that 5% of the total labor force engages in gig economy work. However, a new policy is expected to increase gig economy workers by 15%. How many additional workers will enter the gig economy?]]>
      </text>
    </questiontext>
    <answer fraction="0">
      <text>
        <![CDATA[225,000]]>
      </text>
    </answer>
    <answer fraction="100.000">
      <text>
        <![CDATA[450,000]]>
      </text>
    </answer>
    <answer fraction="0">
      <text>
        <![CDATA[1 million]]>
      </text>
    </answer>
    <answer fraction="0">
      <text>
        <![CDATA[1.5 million]]>
      </text>
    </answer>
    <shuffleanswers>0</shuffleanswers>
    <single>true</single>
    <answernumbering>123</answernumbering>
  </question>
  <!-- Question entry 41 -->
  <question type="multichoice">
    <name>
      <text>
        <![CDATA[__Question 41]]>
      </text>
    </name>
    <questiontext format="html">
      <text>
        <![CDATA[If the total number of poor people in a country is 300 million, and the total population is 1.5 billion, what is the percentage of people living in poverty?]]>
      </text>
    </questiontext>
    <answer fraction="0">
      <text>
        <![CDATA[15%]]>
      </text>
    </answer>
    <answer fraction="100.000">
      <text>
        <![CDATA[20%]]>
      </text>
    </answer>
    <answer fraction="0">
      <text>
        <![CDATA[25%]]>
      </text>
    </answer>
    <answer fraction="0">
      <text>
        <![CDATA[30%]]>
      </text>
    </answer>
    <shuffleanswers>0</shuffleanswers>
    <single>true</single>
    <answernumbering>123</answernumbering>
  </question>
  <!-- Question entry 42 -->
  <question type="multichoice">
    <name>
      <text>
        <![CDATA[__Question 42]]>
      </text>
    </name>
    <questiontext format="html">
      <text>
        <![CDATA[The poverty gap index is a measure that considers how far individuals are from the poverty line. If the poverty line is $2,000 and the average income of the poor is $1,200, what is the poverty gap?]]>
      </text>
    </questiontext>
    <answer fraction="0">
      <text>
        <![CDATA[200]]>
      </text>
    </answer>
    <answer fraction="0">
      <text>
        <![CDATA[500]]>
      </text>
    </answer>
    <answer fraction="100.000">
      <text>
        <![CDATA[800]]>
      </text>
    </answer>
    <answer fraction="0">
      <text>
        <![CDATA[1,200]]>
      </text>
    </answer>
    <shuffleanswers>0</shuffleanswers>
    <single>true</single>
    <answernumbering>123</answernumbering>
  </question>
  <!-- Question entry 43 -->
  <question type="multichoice">
    <name>
      <text>
        <![CDATA[__Question 43]]>
      </text>
    </name>
    <questiontext format="html">
      <text>
        <![CDATA[The headcount ratio is one common method of measuring poverty. If there are 200 individuals in a country and 50 of them earn below the poverty line, what is the headcount ratio?]]>
      </text>
    </questiontext>
    <answer fraction="0">
      <text>
        <![CDATA[0.2]]>
      </text>
    </answer>
    <answer fraction="100.000">
      <text>
        <![CDATA[0.25]]>
      </text>
    </answer>
    <answer fraction="0">
      <text>
        <![CDATA[0.3]]>
      </text>
    </answer>
    <answer fraction="0">
      <text>
        <![CDATA[0.4]]>
      </text>
    </answer>
    <shuffleanswers>0</shuffleanswers>
    <single>true</single>
    <answernumbering>123</answernumbering>
  </question>
  <!-- Question entry 44 -->
  <question type="multichoice">
    <name>
      <text>
        <![CDATA[__Question 44]]>
      </text>
    </name>
    <questiontext format="html">
      <text>
        <![CDATA[The Gini coefficient for Country A is 0.48. If the income distribution in Country A becomes more equal, the Gini coefficient decreases to 0.33. By what percentage has the Gini coefficient decreased?]]>
      </text>
    </questiontext>
    <answer fraction="100.000">
      <text>
        <![CDATA[21.43%]]>
      </text>
    </answer>
    <answer fraction="0">
      <text>
        <![CDATA[15.62%]]>
      </text>
    </answer>
    <answer fraction="0">
      <text>
        <![CDATA[10.42%]]>
      </text>
    </answer>
    <answer fraction="0">
      <text>
        <![CDATA[25.56%]]>
      </text>
    </answer>
    <shuffleanswers>0</shuffleanswers>
    <single>true</single>
    <answernumbering>123</answernumbering>
  </question>
  <!-- Question entry 45 -->
  <question type="multichoice">
    <name>
      <text>
        <![CDATA[__Question 45]]>
      </text>
    </name>
    <questiontext format="html">
      <text>
        <![CDATA[In a population of 1000 individuals, the top 10% earn 60% of total income, while the bottom 50% earn 10%. If the total national income is $500,000, what is the income share of the bottom 50% in dollar terms?]]>
      </text>
    </questiontext>
    <answer fraction="0">
      <text>
        <![CDATA[$50,000]]>
      </text>
    </answer>
    <answer fraction="100.000">
      <text>
        <![CDATA[$30,000]]>
      </text>
    </answer>
    <answer fraction="0">
      <text>
        <![CDATA[$75,000]]>
      </text>
    </answer>
    <answer fraction="0">
      <text>
        <![CDATA[$100,000]]>
      </text>
    </answer>
    <shuffleanswers>0</shuffleanswers>
    <single>true</single>
    <answernumbering>123</answernumbering>
  </question>
  <!-- Question entry 46 -->
  <question type="multichoice">
    <name>
      <text>
        <![CDATA[__Question 46]]>
      </text>
    </name>
    <questiontext format="html">
      <text>
        <![CDATA[If the Lorenz curve for a country shows that the bottom 40% of households earn 10% of the total income, what is the approximate Gini coefficient for that country?]]>
      </text>
    </questiontext>
    <answer fraction="100.000">
      <text>
        <![CDATA[0.60]]>
      </text>
    </answer>
    <answer fraction="0">
      <text>
        <![CDATA[0.45]]>
      </text>
    </answer>
    <answer fraction="0">
      <text>
        <![CDATA[0.50]]>
      </text>
    </answer>
    <answer fraction="0">
      <text>
        <![CDATA[0.40]]>
      </text>
    </answer>
    <shuffleanswers>0</shuffleanswers>
    <single>true</single>
    <answernumbering>123</answernumbering>
  </question>
  <!-- Question entry 47 -->
  <question type="multichoice">
    <name>
      <text>
        <![CDATA[__Question 47]]>
      </text>
    </name>
    <questiontext format="html">
      <text>
        <![CDATA[The income distribution in Country B is represented by a Lorenz curve where the area under the curve is 0.35. What is the Gini coefficient for this country?]]>
      </text>
    </questiontext>
    <answer fraction="0">
      <text>
        <![CDATA[0.30]]>
      </text>
    </answer>
    <answer fraction="100.000">
      <text>
        <![CDATA[0.70]]>
      </text>
    </answer>
    <answer fraction="0">
      <text>
        <![CDATA[0.65]]>
      </text>
    </answer>
    <answer fraction="0">
      <text>
        <![CDATA[0.35]]>
      </text>
    </answer>
    <shuffleanswers>0</shuffleanswers>
    <single>true</single>
    <answernumbering>123</answernumbering>
  </question>
  <!-- Question entry 48 -->
  <question type="multichoice">
    <name>
      <text>
        <![CDATA[__Question 1]]>
      </text>
    </name>
    <questiontext format="html">
      <text>
        <![CDATA[In a population with 1,000 individuals, the income distribution follows a Pareto principle, where the top 20% earn 50% of the total income. If the total income is $1,000,000, what is the income earned by the bottom 80%?]]>
      </text>
    </questiontext>
    <answer fraction="100.000">
      <text>
        <![CDATA[$400,000]]>
      </text>
    </answer>
    <answer fraction="0">
      <text>
        <![CDATA[$500,000]]>
      </text>
    </answer>
    <answer fraction="0">
      <text>
        <![CDATA[$600,000]]>
      </text>
    </answer>
    <answer fraction="0">
      <text>
        <![CDATA[$200,000]]>
      </text>
    </answer>
    <shuffleanswers>0</shuffleanswers>
    <single>true</single>
    <answernumbering>123</answernumbering>
  </question>
  <!-- Question entry 49 -->
  <question type="multichoice">
    <name>
      <text>
        <![CDATA[__Question 1]]>
      </text>
    </name>
    <questiontext format="html">
      <text>
        <![CDATA[The share of total income held by the top 10% of earners in Country Y is 55%. If the total income of the country is $1,000,000, how much income is held by the top 10%?]]>
      </text>
    </questiontext>
    <answer fraction="0">
      <text>
        <![CDATA[$500,000]]>
      </text>
    </answer>
    <answer fraction="100.000">
      <text>
        <![CDATA[$550,000]]>
      </text>
    </answer>
    <answer fraction="0">
      <text>
        <![CDATA[$600,000]]>
      </text>
    </answer>
    <answer fraction="0">
      <text>
        <![CDATA[$450,000]]>
      </text>
    </answer>
    <shuffleanswers>0</shuffleanswers>
    <single>true</single>
    <answernumbering>123</answernumbering>
  </question>
  <!-- Question entry 50 -->
  <question type="multichoice">
    <name>
      <text>
        <![CDATA[__Question 1]]>
      </text>
    </name>
    <questiontext format="html">
      <text>
        <![CDATA[A nation has 5 income quintiles, and the share of income for the top quintile is 50%. The bottom 40% of the population earns 15% of total income. What is the income share of the middle class (the 3rd quintile)?]]>
      </text>
    </questiontext>
    <answer fraction="100.000">
      <text>
        <![CDATA[20%]]>
      </text>
    </answer>
    <answer fraction="0">
      <text>
        <![CDATA[15%]]>
      </text>
    </answer>
    <answer fraction="0">
      <text>
        <![CDATA[10%]]>
      </text>
    </answer>
    <answer fraction="0">
      <text>
        <![CDATA[25%]]>
      </text>
    </answer>
    <shuffleanswers>0</shuffleanswers>
    <single>true</single>
    <answernumbering>123</answernumbering>
  </question>
</quiz>
<!-- Generated with Moodle XML Converter https://moodlexml.fly.dev -->
